<annotation>
	<folder>JPEGImages</folder>
	<filename>449.jpg</filename>
	<source>
		<database>The Defect Detection</database>
		<annotation>Defect Detection</annotation>
		<image>flickr</image>
		<flickrid>NULL</flickrid>
	</source>
	<owner>
		<flickrid>NULL</flickrid>
		<name>WZZ</name>
	</owner>
	<size>
		<width>1024</width>
		<height>1024</height>
		<depth>3</depth>
	</size>
		<segmented>0</segmented>
	<object>
		<name>tomato</name>
		<pose>Unspecified</pose>
		<truncated>1</truncated>
		<difficult>0</difficult>
		<bndbox>
			<xmin>385.6021505376343</xmin>
			<ymin>513.2043010752687</ymin>
			<xmax>463.02150537634407</xmax>
			<ymax>607.8279569892472</ymax>
		</bndbox>
	</object>
	<object>
		<name>tomato</name>
		<pose>Unspecified</pose>
		<truncated>1</truncated>
		<difficult>0</difficult>
		<bndbox>
			<xmin>459.79569892473114</xmin>
			<ymin>523.9569892473118</ymin>
			<xmax>536.1397849462365</xmax>
			<ymax>627.1827956989247</ymax>
		</bndbox>
	</object>
</annotation>